Workbook

Sheet Resumo
A1: Consulta: Salt Vampire
A2: 22/10/2026 · registro em dados/consultas/Salt Vampire.json (motor/consulta.py) · azul: entrada; preto: fórmula; verde: vem de outra aba
A4: Veredito
A5: Em uma frase | B5: Carta mediana: um 2/2 com vínculo e uma espiada na mão que não dá vantagem de carta, porque o oponente compra outra. Não muda nenhum deck; a melhor casa é a Evelyn, numa troca lateral de Vampiro de 2.
A6: Compra | B6: Não | C6: O melhor ganho é +6,25 (Evelyn), abaixo dos 10 que a régua da Caixa pede para Deck. A US$ 12,10 de pré-venda é caro para o que rende. Vale consultar de novo depois de 13/11: se cair perto do preço de bulk, vira 'só se sobrar' para a Evelyn.
A7: Melhor casa pelo motor | B7: =INDEX(Encaixe!$A$5:$A$23,MATCH(MAX(Encaixe!$O$5:$O$23),Encaixe!$O$5:$O$23,0)) -> 02. Evelyn | C7: =MAX(Encaixe!$O$5:$O$23) -> 6.25
A8: Decks na faixa Deck | B8: =COUNTIF(Encaixe!$P$5:$P$23,"Deck") -> 0 | C8: ="ganho de "&TEXT(Régua!$C$22,"0")&" ou mais" -> ganho de 10 ou mais
A9: Decks na faixa Guardar | B9: =COUNTIF(Encaixe!$P$5:$P$23,"Guardar") -> 2 | C9: ="ganho de "&TEXT(Régua!$C$23,"0")&" a "&TEXT(Régua!$C$22,"0") -> ganho de 5 a 10
A10: Decks em avaliar | B10: =COUNTIF(Encaixe!$T$5:$T$23,"avaliar") -> 1 | C10: Evelyn, no lugar do Bloodcrazed Paladin
A11: Decks nas cores da carta | B11: =COUNTA(Encaixe!$A$5:$A$23) -> 19 | C11: 11 decks ficam fora da identidade (sem preto)
A13: A carta
A14: Nome | B14: Salt Vampire
A15: Custo e tipo | B15: {1}{B} · Creature — Vampire Shapeshifter · 2/2
A16: Identidade de cor | B16: Preto (B)
A17: Texto (Scryfall) | B17: Lifelink When this creature enters, look at target opponent's hand. You may choose a nonland card from it. If you do, that player exiles that card, then draws a card.
A18: O que faz de verdade | B18: Não é vantagem de carta: o oponente exila a carta escolhida e compra outra. Você vê a mão e troca a melhor carta dele por uma aleatória; para você, sobra um 2/2 com vínculo.
A19: Coleção | B19: Star Trek (TRK), número 127, rara
A20: Lançamento | B20: 13/11/2026 | C20: Pré-lançamento: o Scryfall ainda a marca como não legal no Commander
A21: Preço (pré-venda) | B21: 12.1 | C21: Scryfall, 22/10/2026; preço de pré-venda
A22: Link | B22: https://scryfall.com/card/trk/127/salt-vampire
A24: Força sozinha
A25: Valor próprio | B25: =Régua!$F$14 -> 3 | C25: os oito critérios da carta, sem sinergia
A26: Mediana do cadastro | B26: 6 | C26: 3.318 cartas em dados/cartas.json, 22/10/2026
A27: Acima de | B27: 0.22 | C27: das cartas do cadastro, pelo valor próprio
A28: Lente Vampiros (Grimório) | B28: 12 | C28: cartas abaixo dela, de 38 com nota na lente
A29: Lente Mono-preto (Grimório) | B29: 3 | C29: cartas abaixo dela, de 38 com nota na lente
A30: EDHREC | B30: #31.419 | C30: pouco dado: a carta ainda não saiu
A31: Game Changer | B31: Não
A33: Armadilhas
A34: Tergrid | B34: O oponente exila a carta da mão, não descarta. A Tergrid só rouba permanente descartada ou sacrificada, então não dispara.
A35: Zumbis, Elfos e Tartarugas | B35: No jogo, o tipo Shapeshifter não dá outros tipos: nota 0. A RUBRICA diz que Shapeshifter conta como da tribo; a decisão é sua (aba Pendências).
A36: K'rrik | B36: O valor alto vem da régua do custo ({B} pago com vida vale 2 para qualquer carta de {1}{B}), não do plano do deck.
A37: Quem sai, pelo motor | B37: É a carta de menor valor do deck inteiro, às vezes uma MDFC que ninguém cortaria. A troca real está em 'Disputa a vaga com' na aba Encaixe.

Sheet Encaixe
A1: Encaixe nos 19 decks nas cores da carta
A2: Azul: entrada. Mude as sinergias (0 a 3) e veja valor, ganho e faixa mudarem. Saturação, quem sai e o valor de quem sai vêm do motor (encaixe.py) em 22/10/2026. Ganho = valor com saturação menos o valor de quem sai.
A4: Deck | B4: Painel | C4: Comandante | D4: Situação | E4: Sin. 1 | F4: Sin. 2 | G4: Sat. Sin. 1 | H4: Sat. Sin. 2 | I4: Sat. Resil. | J4: Sat. Remoção | K4: Valor | L4: Valor com saturação | M4: Quem sai (motor) | N4: Valor de quem sai | O4: Ganho | P4: Faixa | Q4: Disputa a vaga com (na prática) | R4: Valor da comparável | S4: Saldo contra a comparável | T4: Veredito | U4: Porquê do veredito | V4: Porquê das sinergias
A5: 02. Evelyn | B5: Coleção da Cobiça | C5: Evelyn | D5: No acervo | E5: 2 | F5: 0 | G5: 0.5 | H5: 1 | I5: 1.5 | J5: 1 | K5: =Régua!$F$14+Régua!$C$4*INDEX(Régua!$B$17:$B$20,E5+1)+Régua!$C$5*INDEX(Régua!$B$17:$B$20,F5+1) -> 10.5 | L5: =Régua!$C$4*INDEX(Régua!$B$17:$B$20,E5+1)*G5+Régua!$C$5*INDEX(Régua!$B$17:$B$20,F5+1)*H5+Régua!$C$6*INDEX(Régua!$B$17:$B$20,Régua!$D$6+1)*I5+Régua!$C$10*INDEX(Régua!$B$17:$B$20,Régua!$D$10+1)*J5 -> 7.25 | M5: Jwari Disruption | N5: 1 | O5: =L5-N5 -> 6.25 | P5: =IF(O5>=Régua!$C$22,"Deck",IF(O5>=Régua!$C$23,"Guardar","Abaixo")) -> Guardar | Q5: Bloodcrazed Paladin | R5: 8.5 | S5: =IF(R5="","",K5-R5) -> 2 | T5: avaliar | U5: Dispara a coleção ao entrar, como o Paladin, e soma vínculo num deck com Resiliência abaixo da faixa (4 de 5 a 10). Ganha por pouco (10,5 contra 8,5); o Paladin tem lampejo, que ela não tem. | V5: Sin. 1: Vampiro que entra e enche a coleção, sem pôr outro Vampiro em campo (nota 2 da régua).
A6: 01. Vito | B6: Sangria Sagrada | C6: Vito | D6: No acervo | E6: 1 | F6: 1 | G6: 1 | H6: 1 | I6: 1 | J6: 0.5 | K6: =Régua!$F$14+Régua!$C$4*INDEX(Régua!$B$17:$B$20,E6+1)+Régua!$C$5*INDEX(Régua!$B$17:$B$20,F6+1) -> 7 | L6: =Régua!$C$4*INDEX(Régua!$B$17:$B$20,E6+1)*G6+Régua!$C$5*INDEX(Régua!$B$17:$B$20,F6+1)*H6+Régua!$C$6*INDEX(Régua!$B$17:$B$20,Régua!$D$6+1)*I6+Régua!$C$10*INDEX(Régua!$B$17:$B$20,Régua!$D$10+1)*J6 -> 6 | M6: Malakir Rebirth | N6: 1 | O6: =L6-N6 -> 5 | P6: =IF(O6>=Régua!$C$22,"Deck",IF(O6>=Régua!$C$23,"Guardar","Abaixo")) -> Guardar | Q6: Vampire of the Dire Moon | R6: 6 | S6: =IF(R6="","",K6-R6) -> 1 | T6: fora | U6: Vínculo num 2/2 só dispara o Vito em combate, e um 2/2 conecta pouco. Fica 1 ponto acima do Vampire of the Dire Moon: troca que não justifica a compra. | V6: Sin. 1: Vínculo com a vida numa criatura, que só ganha vida em combate (nota 1 da régua, como Gifted Aetherborn). Sin. 2: Vampiro sem efeito voltado aos outros Vampiros (nota 1 da régua).
A7: 03. K'rrik | B7: Dívida & Herança | C7: K'rrik | D7: No acervo | E7: 2 | F7: 1 | G7: 1 | H7: 0.5 | I7: 1 | J7: 0.5 | K7: =Régua!$F$14+Régua!$C$4*INDEX(Régua!$B$17:$B$20,E7+1)+Régua!$C$5*INDEX(Régua!$B$17:$B$20,F7+1) -> 12 | L7: =Régua!$C$4*INDEX(Régua!$B$17:$B$20,E7+1)*G7+Régua!$C$5*INDEX(Régua!$B$17:$B$20,F7+1)*H7+Régua!$C$6*INDEX(Régua!$B$17:$B$20,Régua!$D$6+1)*I7+Régua!$C$10*INDEX(Régua!$B$17:$B$20,Régua!$D$10+1)*J7 -> 10.25 | M7: Ophiomancer | N7: 5.5 | O7: =L7-N7 -> 4.75 | P7: =IF(O7>=Régua!$C$22,"Deck",IF(O7>=Régua!$C$23,"Guardar","Abaixo")) -> Abaixo | Q7: Ophiomancer | R7: 5.5 | S7: =IF(R7="","",K7-R7) -> 6.5 | T7: fora | U7: O número alto vem da régua do custo ({B} pago com vida vale 2 para qualquer carta de {1}{B}). O deck quer feitiço, dreno e remoção; o radar tem mais de 40 cartas na frente para a vaga do Ophiomancer. | V7: Sin. 1: Custo {1}{B}: o K'rrik paga metade do valor de mana com 2 de vida (nota 2 da régua, como Demonic Tutor). Sin. 2: Vínculo com a vida numa criatura (nota 1 da régua).
A8: 01. Markov | B8: Linhagem Vampírica | C8: Edgar | D8: No acervo | E8: 2 | F8: 0 | G8: 0.5 | H8: 0.5 | I8: 1 | J8: 1 | K8: =Régua!$F$14+Régua!$C$4*INDEX(Régua!$B$17:$B$20,E8+1)+Régua!$C$5*INDEX(Régua!$B$17:$B$20,F8+1) -> 10.5 | L8: =Régua!$C$4*INDEX(Régua!$B$17:$B$20,E8+1)*G8+Régua!$C$5*INDEX(Régua!$B$17:$B$20,F8+1)*H8+Régua!$C$6*INDEX(Régua!$B$17:$B$20,Régua!$D$6+1)*I8+Régua!$C$10*INDEX(Régua!$B$17:$B$20,Régua!$D$10+1)*J8 -> 6.75 | M8: Faithless Looting | N8: 3 | O8: =L8-N8 -> 3.75 | P8: =IF(O8>=Régua!$C$22,"Deck",IF(O8>=Régua!$C$23,"Guardar","Abaixo")) -> Abaixo | Q8: Dusk Legion Sergeant | R8: 9.5 | S8: =IF(R8="","",K8-R8) -> 1 | T8: fora | U8: Dispara a eminência como qualquer Vampiro de 2, num deck com 36 Vampiros (sinergia já saturada). O radar tem Stensian Sanguinist, Indulgent Aristocrat e Scheming Silvertongue na frente dela. | V8: Sin. 1: Vampiro que dispara a eminência ao ser conjurado, sem efeito voltado aos outros Vampiros (nota 2 da régua).
A9: 02. Clavileño | B9: Ritos de Sangue | C9: Clavileño | D9: No acervo | E9: 2 | F9: 0 | G9: 0.5 | H9: 0.5 | I9: 1 | J9: 0.5 | K9: =Régua!$F$14+Régua!$C$4*INDEX(Régua!$B$17:$B$20,E9+1)+Régua!$C$5*INDEX(Régua!$B$17:$B$20,F9+1) -> 10.5 | L9: =Régua!$C$4*INDEX(Régua!$B$17:$B$20,E9+1)*G9+Régua!$C$5*INDEX(Régua!$B$17:$B$20,F9+1)*H9+Régua!$C$6*INDEX(Régua!$B$17:$B$20,Régua!$D$6+1)*I9+Régua!$C$10*INDEX(Régua!$B$17:$B$20,Régua!$D$10+1)*J9 -> 5.75 | M9: Malakir Rebirth | N9: 2.5 | O9: =L9-N9 -> 3.25 | P9: =IF(O9>=Régua!$C$22,"Deck",IF(O9>=Régua!$C$23,"Guardar","Abaixo")) -> Abaixo | Q9: Legion Lieutenant | R9: 10.5 | S9: =IF(R9="","",K9-R9) -> 0 | T9: fora | U9: É um Vampiro que ataca e pode ser abençoado, como os outros 30. Fica acima de só 13 das 68 mágicas; os Vampiros de 2 do deck valem de 10,5 a 15. | V9: Sin. 1: Vampiro comum, que ataca e pode ser abençoado, sem pôr outro Vampiro em campo (nota 2 da régua).
A10: 02. Strefan | B10: Baile Carmesim | C10: Strefan | D10: No acervo | E10: 2 | F10: 0 | G10: 0.5 | H10: 0.5 | I10: 1.5 | J10: 0.5 | K10: =Régua!$F$14+Régua!$C$4*INDEX(Régua!$B$17:$B$20,E10+1)+Régua!$C$5*INDEX(Régua!$B$17:$B$20,F10+1) -> 10.5 | L10: =Régua!$C$4*INDEX(Régua!$B$17:$B$20,E10+1)*G10+Régua!$C$5*INDEX(Régua!$B$17:$B$20,F10+1)*H10+Régua!$C$6*INDEX(Régua!$B$17:$B$20,Régua!$D$6+1)*I10+Régua!$C$10*INDEX(Régua!$B$17:$B$20,Régua!$D$10+1)*J10 -> 6.25 | M10: Gamble | N10: 3 | O10: =L10-N10 -> 3.25 | P10: =IF(O10>=Régua!$C$22,"Deck",IF(O10>=Régua!$C$23,"Guardar","Abaixo")) -> Abaixo | Q10: Nullpriest of Oblivion | R10: 12.5 | S10: =IF(R10="","",K10-R10) -> -2 | T10: fora | U10: O Strefan a põe em campo atacando e o efeito de entrada dispara, mas os Vampiros de 2 do deck valem de 12,5 a 16 (Bloodtithe Harvester, Creeping Bloodsucker, Voldaren Bloodcaster). Ela vale 10,5. | V10: Sin. 1: Vampiro que o Strefan põe da mão em campo atacando, sem gatilho a cada Vampiro que entra (nota 2 da régua).
A11: 03. Valgavoth | B11: Dízimo das Almas | C11: Valgavoth | D11: No acervo | E11: 0 | F11: 0 | G11: 1.5 | H11: 1 | I11: 1 | J11: 1 | K11: =Régua!$F$14+Régua!$C$4*INDEX(Régua!$B$17:$B$20,E11+1)+Régua!$C$5*INDEX(Régua!$B$17:$B$20,F11+1) -> 3 | L11: =Régua!$C$4*INDEX(Régua!$B$17:$B$20,E11+1)*G11+Régua!$C$5*INDEX(Régua!$B$17:$B$20,F11+1)*H11+Régua!$C$6*INDEX(Régua!$B$17:$B$20,Régua!$D$6+1)*I11+Régua!$C$10*INDEX(Régua!$B$17:$B$20,Régua!$D$10+1)*J11 -> 3 | M11: Malakir Rebirth | N11: 1 | O11: =L11-N11 -> 2 | P11: =IF(O11>=Régua!$C$22,"Deck",IF(O11>=Régua!$C$23,"Guardar","Abaixo")) -> Abaixo | S11: =IF(R11="","",K11-R11) | T11: fora | U11: Sem ligação com o comandante: vale só como um 2/2 com vínculo. | V11: Nota 0 nas duas sinergias.
A12: 02. Elfos | B12: Selva Élfica | C12: Lathril | D12: No acervo | E12: 0 | F12: 0 | G12: 0.5 | H12: 1 | I12: 1.5 | J12: 1 | K12: =Régua!$F$14+Régua!$C$4*INDEX(Régua!$B$17:$B$20,E12+1)+Régua!$C$5*INDEX(Régua!$B$17:$B$20,F12+1) -> 3 | L12: =Régua!$C$4*INDEX(Régua!$B$17:$B$20,E12+1)*G12+Régua!$C$5*INDEX(Régua!$B$17:$B$20,F12+1)*H12+Régua!$C$6*INDEX(Régua!$B$17:$B$20,Régua!$D$6+1)*I12+Régua!$C$10*INDEX(Régua!$B$17:$B$20,Régua!$D$10+1)*J12 -> 3.5 | M12: Khalni Ambush | N12: 2 | O12: =L12-N12 -> 1.5 | P12: =IF(O12>=Régua!$C$22,"Deck",IF(O12>=Régua!$C$23,"Guardar","Abaixo")) -> Abaixo | S12: =IF(R12="","",K12-R12) | T12: fora | U12: Sem ligação: Shapeshifter não é Elfo no jogo (ver Armadilhas no Resumo). | V12: Nota 0 nas duas sinergias.
A13: 03. Lynde | B13: Chá das Maldições | C13: Lynde | D13: No acervo | E13: 0 | F13: 0 | G13: 1 | H13: 1 | I13: 1.5 | J13: 0.5 | K13: =Régua!$F$14+Régua!$C$4*INDEX(Régua!$B$17:$B$20,E13+1)+Régua!$C$5*INDEX(Régua!$B$17:$B$20,F13+1) -> 3 | L13: =Régua!$C$4*INDEX(Régua!$B$17:$B$20,E13+1)*G13+Régua!$C$5*INDEX(Régua!$B$17:$B$20,F13+1)*H13+Régua!$C$6*INDEX(Régua!$B$17:$B$20,Régua!$D$6+1)*I13+Régua!$C$10*INDEX(Régua!$B$17:$B$20,Régua!$D$10+1)*J13 -> 2.5 | M13: Hydroelectric Specimen | N13: 1 | O13: =L13-N13 -> 1.5 | P13: =IF(O13>=Régua!$C$22,"Deck",IF(O13>=Régua!$C$23,"Guardar","Abaixo")) -> Abaixo | S13: =IF(R13="","",K13-R13) | T13: fora | U13: Sem ligação com o comandante: vale só como um 2/2 com vínculo. | V13: Nota 0 nas duas sinergias.
A14: 04. Assassin Creed | B14: Irmandade Oculta | C14: Ezio | D14: No acervo | E14: 0 | F14: 0 | G14: 1 | H14: 1 | I14: 1.5 | J14: 0.5 | K14: =Régua!$F$14+Régua!$C$4*INDEX(Régua!$B$17:$B$20,E14+1)+Régua!$C$5*INDEX(Régua!$B$17:$B$20,F14+1) -> 3 | L14: =Régua!$C$4*INDEX(Régua!$B$17:$B$20,E14+1)*G14+Régua!$C$5*INDEX(Régua!$B$17:$B$20,F14+1)*H14+Régua!$C$6*INDEX(Régua!$B$17:$B$20,Régua!$D$6+1)*I14+Régua!$C$10*INDEX(Régua!$B$17:$B$20,Régua!$D$10+1)*J14 -> 2.5 | M14: Shay Cormac | N14: 1 | O14: =L14-N14 -> 1.5 | P14: =IF(O14>=Régua!$C$22,"Deck",IF(O14>=Régua!$C$23,"Guardar","Abaixo")) -> Abaixo | S14: =IF(R14="","",K14-R14) | T14: fora | U14: Sem ligação com o comandante: vale só como um 2/2 com vínculo. | V14: Nota 0 nas duas sinergias.
A15: 02. Zumbis | B15: Cortejo Fúnebre | C15: Wilhelt | D15: No acervo | E15: 0 | F15: 0 | G15: 0.5 | H15: 0.5 | I15: 1.5 | J15: 1 | K15: =Régua!$F$14+Régua!$C$4*INDEX(Régua!$B$17:$B$20,E15+1)+Régua!$C$5*INDEX(Régua!$B$17:$B$20,F15+1) -> 3 | L15: =Régua!$C$4*INDEX(Régua!$B$17:$B$20,E15+1)*G15+Régua!$C$5*INDEX(Régua!$B$17:$B$20,F15+1)*H15+Régua!$C$6*INDEX(Régua!$B$17:$B$20,Régua!$D$6+1)*I15+Régua!$C$10*INDEX(Régua!$B$17:$B$20,Régua!$D$10+1)*J15 -> 3.5 | M15: Malakir Rebirth | N15: 2.5 | O15: =L15-N15 -> 1 | P15: =IF(O15>=Régua!$C$22,"Deck",IF(O15>=Régua!$C$23,"Guardar","Abaixo")) -> Abaixo | S15: =IF(R15="","",K15-R15) | T15: fora | U15: Shapeshifter não é Zumbi no jogo: só o Changeling (ou quem copia) ganha os tipos. Nota 0, apesar de a régua dizer que Shapeshifter conta como da tribo (ponto para o dono decidir). | V15: Nota 0 nas duas sinergias.
A16: 03. Master Of Evil | B16: Mestre do Mal | C16: Davros | D16: Precon intacto | E16: 0 | F16: 0 | G16: 1 | H16: 1 | I16: 1 | J16: 0.5 | K16: =Régua!$F$14+Régua!$C$4*INDEX(Régua!$B$17:$B$20,E16+1)+Régua!$C$5*INDEX(Régua!$B$17:$B$20,F16+1) -> 3 | L16: =Régua!$C$4*INDEX(Régua!$B$17:$B$20,E16+1)*G16+Régua!$C$5*INDEX(Régua!$B$17:$B$20,F16+1)*H16+Régua!$C$6*INDEX(Régua!$B$17:$B$20,Régua!$D$6+1)*I16+Régua!$C$10*INDEX(Régua!$B$17:$B$20,Régua!$D$10+1)*J16 -> 2 | M16: The Master, Formed Anew | N16: 1 | O16: =L16-N16 -> 1 | P16: =IF(O16>=Régua!$C$22,"Deck",IF(O16>=Régua!$C$23,"Guardar","Abaixo")) -> Abaixo | S16: =IF(R16="","",K16-R16) | T16: fora | U16: Precon intacto: a lista não muda. | V16: Nota 0 nas duas sinergias.
A17: 04. Queen | B17: Trono Inabalável | C17: Marchesa | D17: No acervo | E17: 0 | F17: 0 | G17: 1 | H17: 1 | I17: 1 | J17: 0.5 | K17: =Régua!$F$14+Régua!$C$4*INDEX(Régua!$B$17:$B$20,E17+1)+Régua!$C$5*INDEX(Régua!$B$17:$B$20,F17+1) -> 3 | L17: =Régua!$C$4*INDEX(Régua!$B$17:$B$20,E17+1)*G17+Régua!$C$5*INDEX(Régua!$B$17:$B$20,F17+1)*H17+Régua!$C$6*INDEX(Régua!$B$17:$B$20,Régua!$D$6+1)*I17+Régua!$C$10*INDEX(Régua!$B$17:$B$20,Régua!$D$10+1)*J17 -> 2 | M17: Approach of the Second Sun | N17: 1 | O17: =L17-N17 -> 1 | P17: =IF(O17>=Régua!$C$22,"Deck",IF(O17>=Régua!$C$23,"Guardar","Abaixo")) -> Abaixo | S17: =IF(R17="","",K17-R17) | T17: fora | U17: Sem ligação com o comandante: vale só como um 2/2 com vínculo. | V17: Nota 0 nas duas sinergias.
A18: 05. Deadpool | B18: 4ª Parede | C18: Deadpool | D18: Desejo | E18: 0 | F18: 0 | G18: 1 | H18: 1.5 | I18: 1 | J18: 1 | K18: =Régua!$F$14+Régua!$C$4*INDEX(Régua!$B$17:$B$20,E18+1)+Régua!$C$5*INDEX(Régua!$B$17:$B$20,F18+1) -> 3 | L18: =Régua!$C$4*INDEX(Régua!$B$17:$B$20,E18+1)*G18+Régua!$C$5*INDEX(Régua!$B$17:$B$20,F18+1)*H18+Régua!$C$6*INDEX(Régua!$B$17:$B$20,Régua!$D$6+1)*I18+Régua!$C$10*INDEX(Régua!$B$17:$B$20,Régua!$D$10+1)*J18 -> 3 | M18: Dark Ritual | N18: 2 | O18: =L18-N18 -> 1 | P18: =IF(O18>=Régua!$C$22,"Deck",IF(O18>=Régua!$C$23,"Guardar","Abaixo")) -> Abaixo | S18: =IF(R18="","",K18-R18) | T18: fora | U18: Deck de Desejo, que não existe fisicamente; e não se liga ao comandante. | V18: Nota 0 nas duas sinergias.
A19: 02. Turtle Power! | B19: Cowabunga | C19: par Leonardo e Michelangelo | D19: No acervo | E19: 0 | F19: 0 | G19: 1 | H19: 0.5 | I19: 1.5 | J19: 1 | K19: =Régua!$F$14+Régua!$C$4*INDEX(Régua!$B$17:$B$20,E19+1)+Régua!$C$5*INDEX(Régua!$B$17:$B$20,F19+1) -> 3 | L19: =Régua!$C$4*INDEX(Régua!$B$17:$B$20,E19+1)*G19+Régua!$C$5*INDEX(Régua!$B$17:$B$20,F19+1)*H19+Régua!$C$6*INDEX(Régua!$B$17:$B$20,Régua!$D$6+1)*I19+Régua!$C$10*INDEX(Régua!$B$17:$B$20,Régua!$D$10+1)*J19 -> 3.5 | M19: Continue? | N19: 3 | O19: =L19-N19 -> 0.5 | P19: =IF(O19>=Régua!$C$22,"Deck",IF(O19>=Régua!$C$23,"Guardar","Abaixo")) -> Abaixo | S19: =IF(R19="","",K19-R19) | T19: fora | U19: Sem ligação: Shapeshifter não é Tartaruga no jogo (ver Armadilhas no Resumo). | V19: Nota 0 nas duas sinergias.
A20: 05. Slivers | B20: Ninho de Enxames | C20: First Sliver | D20: Desejo | E20: 0 | F20: 0 | G20: 0.5 | H20: 1 | I20: 0.5 | J20: 1.5 | K20: =Régua!$F$14+Régua!$C$4*INDEX(Régua!$B$17:$B$20,E20+1)+Régua!$C$5*INDEX(Régua!$B$17:$B$20,F20+1) -> 3 | L20: =Régua!$C$4*INDEX(Régua!$B$17:$B$20,E20+1)*G20+Régua!$C$5*INDEX(Régua!$B$17:$B$20,F20+1)*H20+Régua!$C$6*INDEX(Régua!$B$17:$B$20,Régua!$D$6+1)*I20+Régua!$C$10*INDEX(Régua!$B$17:$B$20,Régua!$D$10+1)*J20 -> 3.5 | M20: Fierce Guardianship | N20: 3 | O20: =L20-N20 -> 0.5 | P20: =IF(O20>=Régua!$C$22,"Deck",IF(O20>=Régua!$C$23,"Guardar","Abaixo")) -> Abaixo | S20: =IF(R20="","",K20-R20) | T20: fora | U20: Deck de Desejo, que não existe fisicamente; e não se liga aos Slivers. | V20: Nota 0 nas duas sinergias.
A21: 02. Kaalia | B21: Céu, Fogo e Inferno | C21: Kaalia | D21: No acervo | E21: 0 | F21: 0 | G21: 1 | H21: 1.5 | I21: 1 | J21: 0.5 | K21: =Régua!$F$14+Régua!$C$4*INDEX(Régua!$B$17:$B$20,E21+1)+Régua!$C$5*INDEX(Régua!$B$17:$B$20,F21+1) -> 3 | L21: =Régua!$C$4*INDEX(Régua!$B$17:$B$20,E21+1)*G21+Régua!$C$5*INDEX(Régua!$B$17:$B$20,F21+1)*H21+Régua!$C$6*INDEX(Régua!$B$17:$B$20,Régua!$D$6+1)*I21+Régua!$C$10*INDEX(Régua!$B$17:$B$20,Régua!$D$10+1)*J21 -> 2 | M21: Fatal Push | N21: 2 | O21: =L21-N21 -> 0 | P21: =IF(O21>=Régua!$C$22,"Deck",IF(O21>=Régua!$C$23,"Guardar","Abaixo")) -> Abaixo | S21: =IF(R21="","",K21-R21) | T21: fora | U21: Sem ligação com o comandante: vale só como um 2/2 com vínculo. | V21: Nota 0 nas duas sinergias.
A22: 03. Tergrid | B22: Lanterna do Medo | C22: Tergrid | D22: No acervo | E22: 0 | F22: 0 | G22: 1 | H22: 1.5 | I22: 1 | J22: 0.5 | K22: =Régua!$F$14+Régua!$C$4*INDEX(Régua!$B$17:$B$20,E22+1)+Régua!$C$5*INDEX(Régua!$B$17:$B$20,F22+1) -> 3 | L22: =Régua!$C$4*INDEX(Régua!$B$17:$B$20,E22+1)*G22+Régua!$C$5*INDEX(Régua!$B$17:$B$20,F22+1)*H22+Régua!$C$6*INDEX(Régua!$B$17:$B$20,Régua!$D$6+1)*I22+Régua!$C$10*INDEX(Régua!$B$17:$B$20,Régua!$D$10+1)*J22 -> 2 | M22: Dark Ritual | N22: 2 | O22: =L22-N22 -> 0 | P22: =IF(O22>=Régua!$C$22,"Deck",IF(O22>=Régua!$C$23,"Guardar","Abaixo")) -> Abaixo | S22: =IF(R22="","",K22-R22) | T22: fora | U22: Armadilha: o oponente exila a carta da mão, não descarta. A Tergrid só rouba permanente descartada ou sacrificada, então não dispara. | V22: Nota 0 nas duas sinergias.
A23: 04. Zur | B23: Equilíbrio Encantado | C23: Zur | D23: No acervo | E23: 0 | F23: 0 | G23: 1 | H23: 1 | I23: 1 | J23: 0.5 | K23: =Régua!$F$14+Régua!$C$4*INDEX(Régua!$B$17:$B$20,E23+1)+Régua!$C$5*INDEX(Régua!$B$17:$B$20,F23+1) -> 3 | L23: =Régua!$C$4*INDEX(Régua!$B$17:$B$20,E23+1)*G23+Régua!$C$5*INDEX(Régua!$B$17:$B$20,F23+1)*H23+Régua!$C$6*INDEX(Régua!$B$17:$B$20,Régua!$D$6+1)*I23+Régua!$C$10*INDEX(Régua!$B$17:$B$20,Régua!$D$10+1)*J23 -> 2 | M23: Judge's Familiar | N23: 2 | O23: =L23-N23 -> 0 | P23: =IF(O23>=Régua!$C$22,"Deck",IF(O23>=Régua!$C$23,"Guardar","Abaixo")) -> Abaixo | S23: =IF(R23="","",K23-R23) | T23: fora | U23: Sem ligação com o comandante: vale só como um 2/2 com vínculo. | V23: Nota 0 nas duas sinergias.
A25: Fora das cores da carta (sem preto), e por isso fora da conta: Giada, Dragões, Goblins, Humanos, Lobos, Heads I win, Fynn, Ken, Zara, Braids e Storm.

Sheet Régua
A1: Régua da pontuação v3 e da Caixa
A2: Fonte: motor/pontuacao.json (pesos e pontos por nota), motor/caixa.json (ganho mínimo) e contexto/pontuacao/RUBRICA.md (notas da carta). Azul: entrada; preto: fórmula.
A3: Critério | B3: Chave | C3: Peso | D3: Nota da Salt Vampire | E3: Pontos | F3: Valor
A4: Sinergia Primária | B4: sin1 | C4: 2.5 | D4: do deck (aba Encaixe)
A5: Sinergia Secundária | B5: sin2 | C5: 1.5 | D5: do deck (aba Encaixe)
A6: Resiliência | B6: resiliencia | C6: 1 | D6: 1 | E6: =INDEX($B$17:$B$20,D6+1) -> 1 | F6: =C6*E6 -> 1
A7: Recurso | B7: recurso | C7: 1 | D7: 0 | E7: =INDEX($B$17:$B$20,D7+1) -> 0 | F7: =C7*E7 -> 0
A8: Draw | B8: draw | C8: 2 | D8: 0 | E8: =INDEX($B$17:$B$20,D8+1) -> 0 | F8: =C8*E8 -> 0
A9: Amplificador | B9: amplificador | C9: 1 | D9: 0 | E9: =INDEX($B$17:$B$20,D9+1) -> 0 | F9: =C9*E9 -> 0
A10: Remoção | B10: remocao | C10: 2 | D10: 1 | E10: =INDEX($B$17:$B$20,D10+1) -> 1 | F10: =C10*E10 -> 2
A11: Evasão | B11: evasao | C11: 1 | D11: 0 | E11: =INDEX($B$17:$B$20,D11+1) -> 0 | F11: =C11*E11 -> 0
A12: Dano Direto | B12: dano | C12: 1 | D12: 0 | E12: =INDEX($B$17:$B$20,D12+1) -> 0 | F12: =C12*E12 -> 0
A13: Aceleradores | B13: aceleradores | C13: 2 | D13: 0 | E13: =INDEX($B$17:$B$20,D13+1) -> 0 | F13: =C13*E13 -> 0
A14: Valor próprio (os oito critérios da carta) | F14: =SUM(F6:F13) -> 3
A16: Nota | B16: Pontos
A17: 0 | B17: 0 | C17: A escala cresce no topo: uma nota 3 vale mais que quatro notas 1.
A18: 1 | B18: 1
A19: 2 | B19: 3
A20: 3 | B20: 6
A22: Ganho mínimo para Deck | C22: 10 | D22: Régua da Caixa (motor/caixa.json, decisão do dono de 17/10/2026)
A23: Ganho mínimo para Guardar | C23: 5
A25: Saturação: o critério do deck abaixo da faixa vale 1,5×, dentro vale 1× e acima vale 0,5×. Os multiplicadores de cada deck estão na aba Encaixe.
A26: A conta com saturação da aba Encaixe usa os quatro critérios em que a carta pontua (Sinergias, Resiliência e Remoção). Nota nova em outro critério muda o valor próprio, mas não a conta com saturação.

Sheet Pendências
A1: Pendências e arquivos
A3: # | B3: Pendência | C3: Como resolver | D3: Quem | E3: Status
A4: 1 | B4: Instalar o comando /consulta | C4: Copiar contexto\consulta\SKILL-consulta.md para .claude\skills\consulta\SKILL.md. No PowerShell, na raiz do projeto: New-Item -ItemType Directory .claude\skills\consulta -Force; Copy-Item contexto\consulta\SKILL-consulta.md .claude\skills\consulta\SKILL.md | D4: Você | E4: Pendente
A5: 2 | B5: Integrar ESTADO.md e ARQUITETURA.md | C5: O texto pronto está no fim de contexto/consulta/CONSULTA.md, em "Para integrar". Não gravei porque outra sessão escrevia nesses arquivos. | D5: Sessão local | E5: Pendente
A6: 3 | B6: Cadastro da Salt Vampire em dados/cartas.json | C6: Entrada pronta no CONSULTA.md (Resiliência 1, Remoção 1). Espera o seu "pode". | D6: Você | E6: Aguardando "pode"
A7: 4 | B7: Commit | C7: O /fechar da outra sessão usa git add -A e leva os arquivos novos. | D7: Sessão local | E7: Pendente
A8: 5 | B8: Rodar o teste no Windows | C8: python testes/consulta.py (34 de 34 na cópia da nuvem; ainda não rodou na sua máquina). | D8: Sessão local | E8: Pendente
A9: 6 | B9: Regra do Shapeshifter | C9: Decidir. Proposta: Changeling conta como da tribo; Shapeshifter só quando copia ou vira a tribo (Irma, Metallic Mimic). | D9: Você | E9: Decisão
A10: 7 | B10: Consultar de novo depois do lançamento | C10: Depois de 13/11/2026: /consulta https://scryfall.com/card/trk/127/salt-vampire. Se o preço cair perto do de bulk, vira 'só se sobrar' para a Evelyn. | D10: Você | E10: A partir de 13/11
A11: 8 | B11: Campo Consultar no Grimório (opcional) | C11: Você cola o link e a página devolve o /consulta pronto para copiar, com o veredito anterior se a carta já foi consultada. Funciona sem internet; pede protótipo antes do código. | D11: Você | E11: Proposta
A14: Arquivos gravados na pasta do projeto em 22/10/2026
A15: # | B15: Arquivo | C15: O que é
A16: 1 | B16: motor/consulta.py | C16: O script: acha a carta, grava o dossiê, calcula o encaixe, grava vereditos e lista as consultas
A17: 2 | B17: testes/consulta.py | C17: O teste: 34 verificações sem rede
A18: 3 | B18: contexto/consulta/CONSULTA.md | C18: O desenho do comando e o texto para integrar
A19: 4 | B19: contexto/consulta/SKILL-consulta.md | C19: O comando, a instalar em .claude/skills/consulta/
A20: 5 | B20: dados/consultas/Salt Vampire.json | C20: O registro desta consulta
A21: 6 | B21: motor/dados.py | C21: consultas entrou em PASTAS_FORA (sem isso, o motor tomaria a pasta por um deck)
A22: 7 | B22: CLAUDE.md | C22: O comando e a pasta nova
A23: 8 | B23: contexto/MODELOS.md | C23: A linha do /consulta (opus, high)
